{
  "id": "MAP_KOUREND_CATACOMBS6",
  "name": "KourendCatacombs6",
  "layout": "LAYOUT_KOUREND_CATACOMBS6",
  "music": "MUS_PS_KOUREND_CATACOMBS",
  "region_map_section": "MAPSEC_LITTLEROOT_TOWN",
  "requires_flash": false,
  "weather": "WEATHER_NONE",
  "map_type": "MAP_TYPE_UNDERGROUND",
  "allow_cycling": true,
  "allow_escaping": true,
  "allow_running": true,
  "show_map_name": false,
  "floor_number": 0,
  "battle_scene": "MAP_BATTLE_SCENE_NORMAL",
  "connections": [
    {
      "map": "MAP_KOUREND_CATACOMBS5",
      "offset": 0,
      "direction": "down"
    },
    {
      "map": "MAP_KOUREND_CATACOMBS2",
      "offset": 0,
      "direction": "right"
    },
    {
      "map": "MAP_KOUREND_CATACOMBS1",
      "offset": 26,
      "direction": "right"
    }
  ],
  "object_events": [
    {
      "type": "object",
      "graphics_id": "OBJ_EVENT_GFX_ITEM_BALL",
      "x": 3,
      "y": 2,
      "elevation": 3,
      "movement_type": "MOVEMENT_TYPE_NONE",
      "movement_range_x": 0,
      "movement_range_y": 0,
      "trainer_type": "TRAINER_TYPE_NONE",
      "trainer_sight_or_berry_tree_id": "0",
      "script": "NULL",
      "flag": "0"
    },
    {
      "type": "object",
      "graphics_id": "OBJ_EVENT_GFX_BREAKABLE_ROCK",
      "x": 12,
      "y": 11,
      "elevation": 3,
      "movement_type": "MOVEMENT_TYPE_NONE",
      "movement_range_x": 0,
      "movement_range_y": 0,
      "trainer_type": "TRAINER_TYPE_NONE",
      "trainer_sight_or_berry_tree_id": "0",
      "script": "NULL",
      "flag": "0"
    },
    {
      "type": "object",
      "graphics_id": "OBJ_EVENT_GFX_POKEMON_373",
      "x": 7,
      "y": 19,
      "elevation": 0,
      "movement_type": "MOVEMENT_TYPE_WANDER_AROUND",
      "movement_range_x": 0,
      "movement_range_y": 0,
      "trainer_type": "TRAINER_TYPE_NONE",
      "trainer_sight_or_berry_tree_id": "0",
      "script": "KourendCatacombs6_RedDragon",
      "flag": "FLAG_HIDE_CATAS_6_RED_DRAGON_2"
    },
    {
      "type": "object",
      "graphics_id": "OBJ_EVENT_GFX_POKEMON_373",
      "x": 5,
      "y": 18,
      "elevation": 0,
      "movement_type": "MOVEMENT_TYPE_WANDER_AROUND",
      "movement_range_x": 0,
      "movement_range_y": 0,
      "trainer_type": "TRAINER_TYPE_NONE",
      "trainer_sight_or_berry_tree_id": "0",
      "script": "KourendCatacombs6_RedDragon",
      "flag": "FLAG_HIDE_CATAS_6_RED_DRAGON_1"
    },
    {
      "type": "object",
      "graphics_id": "OBJ_EVENT_GFX_POKEMON_635",
      "x": 3,
      "y": 7,
      "elevation": 0,
      "movement_type": "MOVEMENT_TYPE_WANDER_AROUND",
      "movement_range_x": 0,
      "movement_range_y": 0,
      "trainer_type": "TRAINER_TYPE_NONE",
      "trainer_sight_or_berry_tree_id": "0",
      "script": "KourendCatacombs6_BlackDragon",
      "flag": "FLAG_HIDE_CATAS_6_BLACK_DRAGON_2"
    },
    {
      "type": "object",
      "graphics_id": "OBJ_EVENT_GFX_POKEMON_635",
      "x": 5,
      "y": 8,
      "elevation": 0,
      "movement_type": "MOVEMENT_TYPE_WANDER_AROUND",
      "movement_range_x": 0,
      "movement_range_y": 0,
      "trainer_type": "TRAINER_TYPE_NONE",
      "trainer_sight_or_berry_tree_id": "0",
      "script": "KourendCatacombs6_BlackDragon",
      "flag": "FLAG_HIDE_CATAS_6_BLACK_DRAGON_1"
    },
    {
      "type": "object",
      "graphics_id": "OBJ_EVENT_GFX_POKEMON_149",
      "x": 12,
      "y": 14,
      "elevation": 0,
      "movement_type": "MOVEMENT_TYPE_WANDER_AROUND",
      "movement_range_x": 0,
      "movement_range_y": 0,
      "trainer_type": "TRAINER_TYPE_NONE",
      "trainer_sight_or_berry_tree_id": "0",
      "script": "KourendCatacombs6_BlueDragon",
      "flag": "FLAG_HIDE_CATAS_6_BLUE_DRAGON_2"
    },
    {
      "type": "object",
      "graphics_id": "OBJ_EVENT_GFX_POKEMON_149",
      "x": 13,
      "y": 17,
      "elevation": 0,
      "movement_type": "MOVEMENT_TYPE_WANDER_AROUND",
      "movement_range_x": 0,
      "movement_range_y": 0,
      "trainer_type": "TRAINER_TYPE_NONE",
      "trainer_sight_or_berry_tree_id": "0",
      "script": "KourendCatacombs6_BlueDragon",
      "flag": "FLAG_HIDE_CATAS_6_BLUE_DRAGON_1"
    }
  ],
  "warp_events": [
    {
      "x": 14,
      "y": 15,
      "elevation": 0,
      "dest_map": "MAP_KOUREND_CATACOMBS2",
      "dest_warp_id": "10"
    }
  ],
  "coord_events": [

  ],
  "bg_events": [
    {
      "type": "hidden_item",
      "x": 11,
      "y": 9,
      "elevation": 3,
      "item": "ITEM_NONE",
      "flag": "FLAG_TEMP_1",
      "quantity": 0,
      "underfoot": false
    }
  ]
}
